snowdrop_tangled_agents/__init__.py
snowdrop_tangled_agents/agents/__init__.py
snowdrop_tangled_agents/agents/random_agent.py
snowdrop_tangled_agents/playing_games/__init__.py
snowdrop_tangled_agents/playing_games/run_local_parallel_tournament.py
snowdrop_tangled_agents/tests/__init__.py
snowdrop_tangled_agents/utils/__init__.py
snowdrop_tangled_agents/utils/utilities.py
snowdrop_tangled_agents-0.0.5.dist-info/licenses/LICENSE
snowdrop_tangled_agents-0.0.5.dist-info/METADATA
snowdrop_tangled_agents-0.0.5.dist-info/WHEEL
snowdrop_tangled_agents-0.0.5.dist-info/RECORD
