Metadata-Version: 2.4
Name: snowdrop-tangled-agents
Version: 0.0.5
Summary: Agents for the Tangled game
License: MIT
License-File: LICENSE
Author: Geordie Rose
Author-email: greatblueheron@users.noreply.github.com
Requires-Python: >=3.11,<3.14
Classifier: License :: OSI Approved :: MIT License
Classifier: Programming Language :: Python :: 3
Classifier: Programming Language :: Python :: 3.11
Classifier: Programming Language :: Python :: 3.12
Classifier: Programming Language :: Python :: 3.13
Requires-Dist: coloredlogs (>=15.0.1)
Requires-Dist: scipy (>=1.16.2)
Requires-Dist: snowdrop-adjudicators (>=0.1.0)
Requires-Dist: snowdrop-tangled-game-engine (>=1.1.0)
Project-URL: Bug Tracker, https://github.com/snowdropquantum/snowdrop-tangled-agents/issues
Project-URL: Documentation, https://github.com/snowdropquantum/snowdrop-tangled-agents
Project-URL: Homepage, https://github.com/snowdropquantum/snowdrop-tangled-agents
Project-URL: Repository, https://github.com/snowdropquantum/snowdrop-tangled-agents
